{
  "languageserver": {
    "golang": {
      "command": "gopls",
      "rootPatterns": ["go.mod", ".vim/", ".git/", ".hg/"],
      "filetypes": ["go"],
      "initializationOptions": {
        "usePlaceholders": true
      }
    }
  },
  "coc.preferences.formatOnSaveFiletypes": [
    "gopls",
    "golang",
    "css",
    "vue",
    "javascriptreact",
    "typescript",
    "Markdown",
    "json",
    "xml",
    "graphql",
    "html",
    "python"
  ],
  "python.formatting.autopep8Path": "/usr/local/bin/autopep8",
  "python.formatting.autopep8Args": ["--max-line-length=200"],
  "tsserver.formatOnType": true,
  "coc.preferences.formatOnType": true,
  "prettier.tslintIntegration": true,
  "prettier.eslintIntegration": true,
  "eslint.autoFixOnSave": true,
  "tslint.autoFixOnSave": true,
  "tslint.exclude": ["~/repo/git.blendlabs.com/blend/lending/backend/dist"],
  "list.normalMappings": {
    "<C-c>": "do:exit"
  }
}
